{
  "name": "Triết học Mác-Lênin - Phần 5",
  "questions": [
    {
      "question": "Ý thức xã hội và ý thức cá nhân có mối quan hệ với nhau như thế nào?",
      "options": [
        "Ý thức xã hội phụ thuộc vào ý thức cá nhân",
        "Ý thức cá nhân phụ thuộc ý thức xã hội",
        "Hai loại hình này độc lập với nhau",
        "Hai loại hình này có mối quan hệ biện chứng"
      ],
      "correct": 0
    },
    {
      "question": "Lực lượng chủ yếu, cơ bản và quyết định mọi thắng lợi của các cuộc cách mạng là:",
      "options": [
        "Quần chúng nhân dân",
        "Cá nhân lãnh tụ",
        "Con người",
        "Giai cấp lãnh đạo"
      ],
      "correct": 0
    },
    {
      "question": "Mặt tinh thần của đời sống xã hội, được gọi là:",
      "options": [
        "Ý thức xã hội",
        "Ý thức văn hóa",
        "Ý thức lý luận",
        "Ý thức đạo đức"
      ],
      "correct": 0
    },
    {
      "question": "Phạm trù nào dưới đây được vận dụng để giải quyết vấn đề cơ bản của triết học trong lĩnh vực xã hội?",
      "options": [
        "Ý thức văn hóa",
        "Ý thức xã hội",
        "Ý thức lý luận",
        "Ý thức đạo đức"
      ],
      "correct": 0
    },
    {
      "question": "Hình thức đấu tranh cao nhất của giai cấp vô sản là:",
      "options": [
        "Kinh tế",
        "Chính trị",
        "Tư tưởng",
        "Kinh tế và chính trị"
      ],
      "correct": 0
    },
    {
      "question": "Yếu tố nào sau đây chỉ hình thức cộng đồng người đầu tiên trong lịch sử loài người?",
      "options": [
        "Bộ lạc",
        "Bộ tộc",
        "Thị tộc",
        "Dân tộc"
      ],
      "correct": 0
    },
    {
      "question": "Hình thức cộng đồng nào có cùng tổ tiên, ngôn ngữ và tín ngưỡng chung?",
      "options": [
        "Dân tộc",
        "Bộ lạc",
        "Bộ tộc",
        "Thị tộc"
      ],
      "correct": 0
    },
    {
      "question": "Sự phân chia giai cấp bắt đầu xuất hiện từ cộng đồng nào?",
      "options": [
        "Thị tộc",
        "Bộ lạc",
        "Dân tộc",
        "Bộ tộc"
      ],
      "correct": 0
    },
    {
      "question": "Sự xuất hiện nhà nước là do nguyên nhân nào?",
      "options": [
        "Kinh tế",
        "Chính trị",
        "Văn hóa",
        "Tư tưởng"
      ],
      "correct": 0
    },
    {
      "question": "Quan hệ sản xuất nào đóng vai trò quyết định đối với một hệ thống sản xuất xã hội?",
      "options": [
        "Quan hệ sản xuất tàn dư",
        "Quan hệ sản xuất thống trị",
        "Quan hệ sản xuất mầm móng",
        "Quan hệ sản xuất tiên tiến"
      ],
      "correct": 0
    },
    {
      "question": "Nội dung nào sau đây quyết định địa vị của các giai cấp trong xã hội.",
      "options": [
        "Quan hệ sản xuất",
        "Lực lượng sản xuất",
        "Cơ sở hạ tầng",
        "Kiến trúc thượng tầng"
      ],
      "correct": 0
    },
    {
      "question": "Mâu thuẫn giữa các cặp yếu nào sau đây là nguồn gốc sâu xa dẫn đến cách mạng xã hội?",
      "options": [
        "Lực lượng sản xuất với quan hệ sản xuất",
        "Giai cấp nô lệ với giai cấp chủ nô",
        "Lĩnh vực kinh tế với lĩnh vực chính trị",
        "Giai cấp bị trị với giai cấp thống trị"
      ],
      "correct": 0
    },
    {
      "question": "Hoạt động nào sau đây là nguyên nhân trực tiếp dẫn đến cách mạng xã hội?",
      "options": [
        "Đấu tranh giai cấp",
        "Đấu tranh chính trị",
        "Đấu tranh quân sự",
        "Đấu tranh kinh tế"
      ],
      "correct": 0
    },
    {
      "question": "Những sự thay đổi căn bản có tính chất toàn bộ mọi mặt của đời sống xã hội được gọi là gì?",
      "options": [
        "Cải cách xã hội",
        "Đấu tranh giai cấp",
        "Cách mạng xã hội",
        "Đảo chính"
      ],
      "correct": 0
    },
    {
      "question": "Đỉnh cao của đấu tranh giai cấp là gì?",
      "options": [
        "Đấu tranh vũ trang",
        "Cách mạng xã hội",
        "Cách mạng bạo lực",
        "Đấu tranh chính trị"
      ],
      "correct": 0
    },
    {
      "question": "Trong mỗi quan hệ giữa tồn tại xã hội và ý thức xã hội yếu tố nào giữ vai trò quyết định?",
      "options": [
        "Tồn tại xã hội giữ vai trò quyết đinh",
        "Ý thức xã hội giữ vai trò quyết định",
        "Có vai trò tác động nganh nhau",
        "Có mỗi quan hệ biện chứng với nhau"
      ],
      "correct": 0
    },
    {
      "question": "Khi điều kiện khách quan và nhân tố chủ quan đã chín muồi thì thời điểm đặc biệt đó của cách mạng được gọi là:",
      "options": [
        "Phương pháp cách mạng",
        "Đối tượng cách mạng",
        "Lực lượng cách mạng",
        "Thời cơ cách mạng"
      ],
      "correct": 0
    },
    {
      "question": "Nội dung nào sau đây thể hiện hình thức đấu tranh kinh tế của giai cấp công nhân?",
      "options": [
        "Đấu tranh đòi tăng lương, cải thiện đời sống",
        "Đấu tranh đòi quyền được ứng cử vào đại biểu quốc hội",
        "Đấu tranh đòi rút ngắn thời gian lao động, đòi quyền tự do",
        "Đấu tranh đòi tăng lương, xóa bỏ tư tưởng lạc hậu"
      ],
      "correct": 0
    },
    {
      "question": "Nội dung nào sau đây thể hiện hình thức đấu tranh chính trị của giai cấp công nhân?",
      "options": [
        "Mít-tinh biểu tình đòi tăng lương, giảm giờ làm",
        "Mít-tinh, biểu tình, bãi công chính trị",
        "Mít-tinh, biểu tình đòi rút ngắn thời gian lao động",
        "Mít-tinh, biểu tình cải thiện điều kiện làm việc"
      ],
      "correct": 0
    },
    {
      "question": "Trong các nguyên nhân dưới đây, nguyên nhân nào gây nên hiện tượng tha hóa con người?",
      "options": [
        "Giai cấp thống trị đàn áp giai cấp bị trị",
        "Xuất hiện chế độ tư hữu về tư liệu sản xuất",
        "Sự bất công, bất bình đẳng trong xã hội",
        "Pháp luật chưa nghiêm"
      ],
      "correct": 0
    },
    {
      "question": "Theo quan điểm của C.Mác, yếu tố nào là nguồn gốc của cơ cấu xã hội- giai cấp.",
      "options": [
        "Chính trị",
        "Văn hóa",
        "Quyền lực",
        "Kinh tế"
      ],
      "correct": 0
    },
    {
      "question": "Tâm lý xã hội và hệ tư tưởng có mối quan hệ với nhau như thế nào?",
      "options": [
        "Phụ thuộc lẫn nhau",
        "Đan xen lẫn nhau",
        "Độc lập với nhau",
        "Tác động lẫn nhau"
      ],
      "correct": 0
    },
    {
      "question": "Khi các quan hệ xã hội thay đổi thì bản chất của con người sẽ như thế nào?",
      "options": [
        "Vẫn không thay đổi",
        "Thay đổi đồng thời với sự thay đổi của các quan hệ xã hội",
        "Ít hay nhiều, sớm hay muộn cũng thay đổi theo",
        "Thay đổi rất chậm"
      ],
      "correct": 0
    },
    {
      "question": "Loại ý thức nào phản ánh một cách sinh động, trực tiếp và chưa được khái quát hóa các mặt khác nhau trong cuộc sống hằng ngày của con người?",
      "options": [
        "Ý thức xã hội thông thường",
        "Ý thức lý luận",
        "Ý thức khoa học",
        "Hệ tư tưởng"
      ],
      "correct": 0
    },
    {
      "question": "Theo quan điểm của triết học Mác-Lênin, đấu tranh giai cấp sẽ:",
      "options": [
        "Tất yếu dẫn đến chuyên chính vô sản",
        "Làm cho xã hội ngày càng văn minh hơn",
        "Làm giảm tham ô, hối lộ trong bộ máy nhà nước",
        "Chỉ có trong xã hội tư bản"
      ],
      "correct": 0
    }
  ]
}